logsmal/__init__.py
logsmal/helpful.py
logsmal/independent/README.md
logsmal/independent/__init__.py
logsmal/independent/helpful.py
logsmal/independent/log_file.py
logsmal/independent/zip_file.py
logsmal/log_row.py
logsmal/logsmal.py
logsmal-0.0.15.dist-info/WHEEL
logsmal-0.0.15.dist-info/METADATA
logsmal-0.0.15.dist-info/RECORD
