Metadata-Version: 2.1
Name: logsmal
Version: 0.0.15
Summary: Создание файлов конфигураци
Home-page: https://github.com/denisxab/logsmal.git
Author: Denis Kustov
Author-email: denis-kustov@rambler.ru
Requires-Python: >=3.10,<4.0
Classifier: Programming Language :: Python :: 3
Classifier: Programming Language :: Python :: 3.10
Classifier: Programming Language :: Python :: 3.11
Requires-Dist: jsonpickle (>=2.2.0,<3.0.0)
Requires-Dist: pydantic (>=1.10.2,<2.0.0)
Requires-Dist: rich (>=12.6.0,<13.0.0)
Project-URL: Documentation, https://logsmal.readthedocs.io/ru/latest/index.html
Project-URL: Repository, https://github.com/denisxab/logsmal.git
